propose/VERSION
propose/__init__.py
propose/ast/__init__.py
propose/ast/_and.py
propose/ast/_or.py
propose/ast/and.py
propose/ast/biconditional.py
propose/ast/binary.py
propose/ast/binary_operation.py
propose/ast/expression.py
propose/ast/f.py
propose/ast/false.py
propose/ast/formula.py
propose/ast/implication.py
propose/ast/literal.py
propose/ast/negation.py
propose/ast/node.py
propose/ast/or.py
propose/ast/t.py
propose/ast/true.py
propose/ast/unary.py
propose/ast/unary_operation.py
propose/ast/xor.py
propose/builder/__init__.py
propose/errors/__init__.py
propose/errors/error_handler.py
propose/errors/lexing_error.py
propose/errors/parsing_error.py
propose/lexer/__init__.py
propose/lexer/lexer.py
propose/parser/__init__.py
propose/parser/parser.py
propose/parser/state.py
propose/renderer/__init__.py
propose/renderer/ast.py
propose/renderer/tokens.py
test/__init__.py
test/test_builder.py
test/test_parser.py
propose-0.1.0a0.dist-info/LICENSE
propose-0.1.0a0.dist-info/METADATA
propose-0.1.0a0.dist-info/WHEEL
propose-0.1.0a0.dist-info/entry_points.txt
propose-0.1.0a0.dist-info/top_level.txt
propose-0.1.0a0.dist-info/RECORD
