Metadata-Version: 2.1
Name: propose
Version: 0.1.0a0
Summary: Build truthtables with your command line
Home-page: UNKNOWN
Author: Jonas Hübotter
Author-email: me@jonhue.me
License: UNKNOWN
Project-URL: Bug Reports, https://github.com/jonhue/propose/issues
Project-URL: Source, https://github.com/jonhue/propose
Platform: UNKNOWN
Classifier: Development Status :: 3 - Alpha
Classifier: Programming Language :: Python :: 3.6
Requires-Dist: colorama (==0.4.1)
Requires-Dist: docopt (==0.6.2)
Requires-Dist: rply (==0.7.6)
Provides-Extra: dev
Requires-Dist: pytest (==4.1.0) ; extra == 'dev'
